lidtk/__init__.py
lidtk/cli.py
lidtk/config.yaml
lidtk/features.py
lidtk/get_predictions.py
lidtk/utils.py
lidtk/analysis/__init__.py
lidtk/analysis/unicode_block.py
lidtk/classifiers/__init__.py
lidtk/classifiers/char_features.py
lidtk/classifiers/cld2_mod.py
lidtk/classifiers/google_mod.py
lidtk/classifiers/langdetect_mod.py
lidtk/classifiers/langid_mod.py
lidtk/classifiers/mlp.py
lidtk/classifiers/text_cat.py
lidtk/classifiers/tfidf_features.py
lidtk/classifiers/tfidf_nn.py
lidtk/classifiers/char_distribution/__init__.py
lidtk/classifiers/char_distribution/char_dist_metric_train_test.py
lidtk/classifiers/config/cld2.yaml
lidtk/classifiers/config/google-cloud.yaml
lidtk/classifiers/config/langdetect.yaml
lidtk/classifiers/config/langid.yaml
lidtk/classifiers/config/textcat.yaml
lidtk/classifiers/config/tfidf_nn.yaml
lidtk/classifiers/config/tfidf_nn_big.yaml
lidtk/classifiers/config/tfidf_nn_case_sensitive.yaml
lidtk/classifiers/nn/__init__.py
lidtk/data/__init__.py
lidtk/data/char_distribution.py
lidtk/data/create_ml_dataset.py
lidtk/data/download_documents.py
lidtk/data/language_utils.py
lidtk/data/pickle_to_txt.py
lidtk/data/wili.py
lidtk/models/__init__.py
lidtk/models/detectlanguage.csv
lidtk/models/service_cld2.py
lidtk/models/service_detectlanguage.py
lidtk-0.3.0.dist-info/LICENSE
lidtk-0.3.0.dist-info/METADATA
lidtk-0.3.0.dist-info/WHEEL
lidtk-0.3.0.dist-info/entry_points.txt
lidtk-0.3.0.dist-info/top_level.txt
lidtk-0.3.0.dist-info/RECORD
