Metadata-Version: 2.1
Name: lidtk
Version: 0.3.0
Summary: Language identification Toolkit
Home-page: https://github.com/MartinThoma/language-identification
Author: Martin Thoma
Author-email: info@martin-thoma.de
Maintainer: Martin Thoma
Maintainer-email: info@martin-thoma.de
License: MIT
Download-URL: https://github.com/MartinThoma/language-identification
Keywords: Machine Learning,Data Science
Platform: Linux
Classifier: Development Status :: 7 - Inactive
Classifier: Environment :: Console
Classifier: Intended Audience :: Developers
Classifier: Intended Audience :: Science/Research
Classifier: Intended Audience :: Information Technology
Classifier: License :: OSI Approved :: MIT License
Classifier: Natural Language :: English
Classifier: Programming Language :: Python :: 3
Classifier: Programming Language :: Python :: 3 :: Only
Classifier: Programming Language :: Python :: 3.6
Classifier: Programming Language :: Python :: 3.7
Classifier: Programming Language :: Python :: 3.8
Classifier: Topic :: Scientific/Engineering :: Information Analysis
Classifier: Topic :: Software Development
Classifier: Topic :: Utilities
Requires-Python: >=3.6
Requires-Dist: cld2-cffi
Requires-Dist: click
Requires-Dist: detectlanguage
Requires-Dist: fuzzywuzzy
Requires-Dist: python-Levenshtein
Requires-Dist: h5py
Requires-Dist: Keras (<2.4.0)
Requires-Dist: langdetect
Requires-Dist: langid
Requires-Dist: matplotlib
Requires-Dist: nltk
Requires-Dist: numpy
Requires-Dist: progressbar2
Requires-Dist: PyYAML
Requires-Dist: scikit-learn
Requires-Dist: scipy
Requires-Dist: seaborn
Requires-Dist: tensorflow
Requires-Dist: wikipedia
